examples/__init__.py
examples/egnn.py
stcrpy/__init__.py
stcrpy/tcr_datasets/__init__.py
stcrpy/tcr_datasets/tcr_graph_dataset.py
stcrpy/tcr_datasets/tcr_selector.py
stcrpy/tcr_datasets/tcr_structure_dataset.py
stcrpy/tcr_datasets/utils.py
stcrpy/tcr_formats/__init__.py
stcrpy/tcr_formats/tcr_formats.py
stcrpy/tcr_formats/tcr_haddock.py
stcrpy/tcr_geometry/TCRAngle.py
stcrpy/tcr_geometry/TCRCoM.py
stcrpy/tcr_geometry/TCRCoM_LICENCE
stcrpy/tcr_geometry/TCRDock.py
stcrpy/tcr_geometry/TCRGeom.py
stcrpy/tcr_geometry/TCRGeomFiltering.py
stcrpy/tcr_geometry/__init__.py
stcrpy/tcr_geometry/reference_data/Acoreset.txt
stcrpy/tcr_geometry/reference_data/Bcoreset.txt
stcrpy/tcr_geometry/reference_data/__init__.py
stcrpy/tcr_geometry/reference_data/consensus_A.pdb
stcrpy/tcr_geometry/reference_data/consensus_B.pdb
stcrpy/tcr_geometry/reference_data/consensus_D.pdb
stcrpy/tcr_geometry/reference_data/consensus_G.pdb
stcrpy/tcr_geometry/reference_data/dock_reference_1_imgt_numbered.pdb
stcrpy/tcr_geometry/reference_data/dock_reference_2_imgt_numbered.pdb
stcrpy/tcr_geometry/reference_data/pcA.txt
stcrpy/tcr_geometry/reference_data/pcB.txt
stcrpy/tcr_geometry/reference_data/reference_A.pdb
stcrpy/tcr_geometry/reference_data/reference_B.pdb
stcrpy/tcr_geometry/reference_data/reference_D.pdb
stcrpy/tcr_geometry/reference_data/reference_G.pdb
stcrpy/tcr_geometry/reference_data/reference_data.py
stcrpy/tcr_interactions/PLIPParser.py
stcrpy/tcr_interactions/TCRInteractionProfiler.py
stcrpy/tcr_interactions/TCRpMHC_PLIP_Model_Parser.py
stcrpy/tcr_interactions/__init__.py
stcrpy/tcr_interactions/utils.py
stcrpy/tcr_methods/__init__.py
stcrpy/tcr_methods/tcr_batch_operations.py
stcrpy/tcr_methods/tcr_methods.py
stcrpy/tcr_methods/tcr_reformatting.py
stcrpy/tcr_metrics/__init__.py
stcrpy/tcr_metrics/constants.py
stcrpy/tcr_metrics/tcr_dockq.py
stcrpy/tcr_metrics/tcr_interface_rmsd.py
stcrpy/tcr_metrics/tcr_rmsd.py
stcrpy/tcr_ml/__init__.py
stcrpy/tcr_ml/geometry_predictor.py
stcrpy-1.0.5.dist-info/licenses/LICENCE
stcrpy-1.0.5.dist-info/licenses/stcrpy/tcr_geometry/TCRCoM_LICENCE
stcrpy-1.0.5.dist-info/METADATA
stcrpy-1.0.5.dist-info/WHEEL
stcrpy-1.0.5.dist-info/top_level.txt
stcrpy-1.0.5.dist-info/RECORD
