Metadata-Version: 2.4
Name: stcrpy
Version: 1.0.5
Summary: Set of methods to parse, annotate, and calculate features of TCR structures
Maintainer-email: Nele Quast <quast@stats.ox.ac.uk>
Requires-Python: >=3.10
License-File: LICENCE
License-File: stcrpy/tcr_geometry/TCRCoM_LICENCE
Requires-Dist: biopython
Requires-Dist: numpy==1.26.4
Requires-Dist: lxml
Requires-Dist: openbabel-wheel==3.1.1.21
Requires-Dist: rdkit
Requires-Dist: anarci-mhc
Requires-Dist: pandas
Requires-Dist: matplotlib
Requires-Dist: scipy
Requires-Dist: requests
Requires-Dist: scikit-learn
Requires-Dist: DockQ
Provides-Extra: ml-datasets
Requires-Dist: einops; extra == "ml-datasets"
Requires-Dist: torch; extra == "ml-datasets"
Requires-Dist: torch_geometric; extra == "ml-datasets"
Dynamic: license-file
